pelican_metadata_generator/__init__.py
pelican_metadata_generator/cli.py
pelican_metadata_generator/controller.py
pelican_metadata_generator/file_handler.py
pelican_metadata_generator/model.py
pelican_metadata_generator/view.py
pelican_metadata_generator-0.2.1.dist-info/LICENSE
pelican_metadata_generator-0.2.1.dist-info/METADATA
pelican_metadata_generator-0.2.1.dist-info/WHEEL
pelican_metadata_generator-0.2.1.dist-info/entry_points.txt
pelican_metadata_generator-0.2.1.dist-info/RECORD
