Metadata-Version: 2.3
Name: pelican-metadata-generator
Version: 0.2.1
Summary: 
License: AGPL-3.0-or-later
Author: Mirek Długosz
Author-email: mirek@mirekdlugosz.com
Requires-Python: >=3.9
Classifier: License :: OSI Approved :: GNU Affero General Public License v3 or later (AGPLv3+)
Classifier: Programming Language :: Python :: 3
Classifier: Programming Language :: Python :: 3.9
Classifier: Programming Language :: Python :: 3.10
Classifier: Programming Language :: Python :: 3.11
Classifier: Programming Language :: Python :: 3.12
Classifier: Programming Language :: Python :: 3.13
Provides-Extra: dev
Requires-Dist: PyQt5 (>=5.15.0,<6.0.0)
Requires-Dist: PyQt5-Qt5 (>=5.15.2,<6.0.0)
Requires-Dist: black (>=24.2.0,<25.0.0) ; extra == "dev"
Requires-Dist: flake8 (>=7.0.0,<8.0.0) ; extra == "dev"
Requires-Dist: pytest (>=8.0.1,<9.0.0) ; extra == "dev"
Requires-Dist: python-slugify (>=8.0.4,<9.0.0)
Project-URL: Repository, https://github.com/mirekdlugosz/pelican-metadata-generator
